datagenix/__init__.py
datagenix/generator.py
datagenix-0.1.2.dist-info/METADATA
datagenix-0.1.2.dist-info/WHEEL
datagenix-0.1.2.dist-info/top_level.txt
datagenix-0.1.2.dist-info/RECORD
